MANIFEST.in
README.TXT
distribute_setup.py
setup.py
doc/Makefile
doc/ami.rst
doc/arch.png
doc/changelog.rst
doc/cli_ref_top.rst
doc/conf.py
doc/config_ref_top.rst
doc/developer.rst
doc/docs.rst
doc/download.rst
doc/ec2.rst
doc/example_cluster.png
doc/example_mini_clusters.png
doc/figures.odg
doc/gen_ami_page.py
doc/gen_cli_doc.py
doc/gen_config_doc.py
doc/gen_recipe_doc.py
doc/gen_samples.py
doc/gen_topology_doc.py
doc/go.rst
doc/guide_autocomplete.rst
doc/guide_compute_go.rst
doc/guides.rst
doc/index.rst
doc/install.rst
doc/instance_operations.rst
doc/intro.rst
doc/intro_common.rst
doc/quickstart.rst
doc/recipe_ref_top.rst
doc/stopology_ref_top.rst
doc/support.rst
doc/topology.rst
doc/topology_ref_top.rst
doc/whatis.rst
doc/_static/logo.png
doc/_templates/layout.html
doc/_templates/quickstart.html
samples/dummy.conf
samples/ec2.conf
samples/go-condor-ec2.conf
samples/go-gridftp-ec2.conf
samples/simple-dummy.conf
samples/simple-ec2-hadoop.conf
samples/simple-ec2.conf
samples/single-gridftp-ec2.conf
scripts/gp-complete.sh
src/dg_paraproxy/WrapSock.py
src/dg_paraproxy/__init__.py
src/globus/__init__.py
src/globus/provision/__init__.py
src/globus/provision/chef-files/README.md
src/globus/provision/chef-files/apt/README.md
src/globus/provision/chef-files/apt/metadata.json
src/globus/provision/chef-files/apt/metadata.rb
src/globus/provision/chef-files/apt/files/default/apt-proxy-v2.conf
src/globus/provision/chef-files/apt/providers/repository.rb
src/globus/provision/chef-files/apt/recipes/cacher-client.rb
src/globus/provision/chef-files/apt/recipes/cacher-ng.rb
src/globus/provision/chef-files/apt/recipes/default.rb
src/globus/provision/chef-files/apt/resources/repository.rb
src/globus/provision/chef-files/cookbooks/R/README.rdoc
src/globus/provision/chef-files/cookbooks/R/metadata.rb
src/globus/provision/chef-files/cookbooks/R/recipes/Rlibs-dir-common.rb
src/globus/provision/chef-files/cookbooks/R/recipes/Rlibs-dir.rb
src/globus_provision.egg-info/PKG-INFO
src/globus_provision.egg-info/SOURCES.txt
src/globus_provision.egg-info/dependency_links.txt
src/globus_provision.egg-info/entry_points.txt
src/globus_provision.egg-info/not-zip-safe
src/globus_provision.egg-info/requires.txt
src/globus_provision.egg-info/top_level.txt